macv_metrics/__init__.py
macv_metrics/metrics.py
macv_metrics-0.1.0.dist-info/licenses/LICENSE
macv_metrics-0.1.0.dist-info/METADATA
macv_metrics-0.1.0.dist-info/WHEEL
macv_metrics-0.1.0.dist-info/top_level.txt
macv_metrics-0.1.0.dist-info/RECORD
